{
  "BeraTrax": {
    "status": "Testnet",
    "sources": [
      {
        "link": "https://bartio.faucet.berachain.com/",
        "description": "Faucet"
      },
      {
        "link": "https://testnet.beratrax.com/CopularBera",
        "description": "Register"
      }
    ]
  },
  "Voltix AI": {
    "status": "depin airdrop",
    "sources": [
      {
        "link": "https://voltix.ai/login",
        "description": "Register"
      }
    ]
  },
  "Patriot": {
    "status": "Galxe Quest",
    "sources": [
      {
        "link": "https://app.galxe.com/quest/PatriotCoin/GCF8mtpwsM?referral_code=GRFr2JFwLKm-UnIgZtxEaWg2HRrDVij3vbvCT_UEoK_oqBQ",
        "description": "Register"
      }
    ]
  }
}